README.rst
setup.py
SortedSet/__init__.py
SortedSet/sorted_set.py
SortedSet.egg-info/PKG-INFO
SortedSet.egg-info/SOURCES.txt
SortedSet.egg-info/dependency_links.txt
SortedSet.egg-info/top_level.txt