Metadata-Version: 2.1
Name: SortedSet
Version: 0.4
Summary: Implementation of Immutable Sorted Set collection
Home-page: https://github.com/urosjevremovic/SortedSetCollection
Author: Uros Jevremovic
Author-email: jevremovic.uros91@gmail.com
License: MIT
Platform: UNKNOWN
